ccc_cli/__init__.py
ccc_cli/ccc6_print_task_runs.py
ccc_cli-0.1.3.dist-info/entry_points.txt
ccc_cli-0.1.3.dist-info/LICENSE
ccc_cli-0.1.3.dist-info/WHEEL
ccc_cli-0.1.3.dist-info/METADATA
ccc_cli-0.1.3.dist-info/RECORD
