Metadata-Version: 2.1
Name: ccc-cli
Version: 0.1.3
Summary: Command line utility for Carbon Copy Cloner
Home-page: https://github.com/tddschn/ccc-cli
License: MIT
Keywords: git,asyncio
Author: Xinyuan Chen
Author-email: 45612704+tddschn@users.noreply.github.com
Requires-Python: >=3.10,<4.0
Classifier: License :: OSI Approved :: MIT License
Classifier: Programming Language :: Python :: 3
Classifier: Programming Language :: Python :: 3.10
Requires-Dist: tabulate (>=0.8.9,<0.9.0)
Project-URL: Bug Tracker, https://github.com/tddschn/ccc-cli/issues
Project-URL: Repository, https://github.com/tddschn/ccc-cli
